[
  {
    "talkie": "최근에 어떤 일을 하고 계신가요?"
  },
  {
    "talkie": "요즘 관심 가지고 있는 일이나 취미는 무엇인가요?"
  },
  {
    "talkie": "가족  & 친구들과 최근에 함께한 즐거운 일이 있나요?"
  },
  {
    "talkie": "최근에 본 영화나 드라마 & 책 중에서 추천할 만한 작품이 있나요?"
  },
  {
    "talkie": "가장 기억에 남는 여행 경험은 어떤 것이었나요?"
  },
  {
    "talkie": "최근에 새로운 사람을 만나게 된 적이 있나요? 어떤 사람이었나요?"
  },
  {
    "talkie": "최근에 배운 것이나 새롭게 시작한 일이 있나요?"
  },
  {
    "talkie": "일상에서 특별히 기분 좋은 순간이 있었나요?"
  },
  {
    "talkie": "최근에 스트레스를 받거나 어려움을 겪은 일이 있었나요? 어떻게 극복했나요?"
  },
  {
    "talkie": "평소에 자주 듣는 음악이나 팟캐스트가 있나요? 추천해주세요."
  },
  {
    "talkie": "요즘에는 어떤 습관을 신경쓰고 있나요?"
  },
  {
    "talkie": "최근에 맛있게 먹은 음식이나 카페가 있나요? 추천해주세요."
  },
  {
    "talkie": "가장 가까운 친구들과 어떤 일을 같이 하면서 재미있게 놀았나요?"
  },
  {
    "talkie": "앞으로 어떤 계획이 있나요? 무엇을 하고 싶은지 & 무엇을 추구하고 싶은지 등을 이야기해보세요."
  },
  {
    "talkie": "오늘 날씨가 어때요?"
  },
  {
    "talkie": "가장 좋아하는 날씨는 무엇인가요?"
  },
  {
    "talkie": "계절별로 어떤 날씨가 편안한가요?"
  },
  {
    "talkie": "여름철 무더운 날씨를 이겨내는 방법은 무엇인가요?"
  },
  {
    "talkie": "추운 겨울에는 어떤 옷을 입어야 할까요?"
  },
  {
    "talkie": "눈이 내린다면 무엇을 하시나요?"
  },
  {
    "talkie": "비가 오는 날씨 좋아하세요?"
  },
  {
    "talkie": "햇볕이 좋은 날씨에는 어떤 액티비티를 추천하시나요?"
  },
  {
    "talkie": "날씨가 좋을 때 가장 좋아하는 야외활동은 무엇인가요?"
  },
  {
    "talkie": "날씨에 따라 기분이 달라지나요?"
  },
  {
    "talkie": "가장 재미있게 플레이한 게임은 무엇인가요?"
  },
  {
    "talkie": "어떤 게임을 자주 플레이하나요?"
  },
  {
    "talkie": "게임을 플레이할 때 선호하는 장르는 무엇인가요?"
  },
  {
    "talkie": "게임에서 가장 좋아하는 기능이나 요소는 무엇인가요?"
  },
  {
    "talkie": "여러분의 모바일 게임 추천은 무엇인가요?"
  },
  {
    "talkie": "롤토체스 좋아하세요? (내가 하는 게임)"
  },
  {
    "talkie": "가장 좋아하는 음식은 무엇인가요?"
  },
  {
    "talkie": "새로운 음식을 시도해 본 적이 있나요? 어떤 음식이었나요? 맛은 어땠나요?"
  },
  {
    "talkie": "가장 좋아하는 음식점은 어디인가요? 그곳에서 추천하는 메뉴는 무엇인가요?"
  },
  {
    "talkie": "못 먹는 식재료나 음식 있어요?"
  },
  {
    "talkie": "여행 스타일이 어떻게 되세요?"
  },
  {
    "talkie": "혼자 VS 함께"
  },
  {
    "talkie": "자유 여행VS 가이드 투어?"
  },
  {
    "talkie": "가장 좋아하는 여행지는 어디인가요? 그곳에서 가장 좋았던 경험은 무엇이었나요?"
  },
  {
    "talkie": "혼자 여행을 가보신 적이 있나요? 어떤 경험이었나요?"
  },
  {
    "talkie": "가족과 함께 여행을 가보신 적이 있나요? 어떤 곳으로 갔나요?"
  },
  {
    "talkie": "해외 여행을 가보신 적이 있나요? 어느 나라를 방문했나요?"
  },
  {
    "talkie": "여행 중 가장 기억에 남는 일은 무엇인가요?"
  },
  {
    "talkie": "여행지에서 놓치지 못할 것은 무엇인가요? 특별한 행사 & 특산품 & 관광명소 & 음식 & 쇼핑 & 휴식"
  },
  {
    "talkie": "다음에 가보고 싶은 여행지는 어디인가요? 그곳에서 하고 싶은 것은 무엇인가요?"
  },
  {
    "talkie": "여행 중 가장 좋아하는 사진 한 장을 보여주세요! 그 사진에 담긴 이야기는 무엇인가요?"
  },
  {
    "talkie": "어떤 종류의 운동을 좋아하나요?"
  },
  {
    "talkie": "운동을 시작한 계기가 무엇이었나요?"
  },
  {
    "talkie": "운동하는 동안에 가장 중요하게 생각하는 것은 무엇인가요?"
  },
  {
    "talkie": "운동을 하기 전에 준비하는 것이 있나요?"
  },
  {
    "talkie": "운동을 하면서 얻은 가장 큰 변화는 무엇인가요?"
  },
  {
    "talkie": "현재 목표로 삼고 있는 운동 목표는 무엇인가요?"
  },
  {
    "talkie": "가장 힘들게 느꼈던 운동은 무엇이었나요?"
  },
  {
    "talkie": "운동 시간대는 언제인가요? 아침에 운동하는 것이 좋은 것 같나요?"
  },
  {
    "talkie": "운동을 하면서 듣는 음악은 무엇인가요?"
  },
  {
    "talkie": "운동을 하면서 건강 식습관을 유지하는 방법은 무엇인가요?"
  },
  {
    "talkie": "얼마나 자주 운동 하세요?"
  },
  {
    "talkie": "Mbti가 어떻게 되세요?"
  },
  {
    "talkie": "MBTI 유형 결과를 처음 알게 되었을 때 어떤 감정을 느꼈나요?"
  },
  {
    "talkie": "MBTI 유형 결과가 당신의 인생이나 직장에서 어떤 영향을 미치는지 생각해봤나요?"
  },
  {
    "talkie": "당신의 MBTI 유형과 비슷한 사람들과 어떻게 지내시나요? 서로의 성격이 어떻게 다르거나 비슷한지 느끼시나요?"
  },
  {
    "talkie": "MBTI 유형이 당신의 강점이나 약점을 나타내는 데에 도움이 되는지 어떻게 생각하시나요?"
  },
  {
    "talkie": "당신이 알고 있는 사람들 중에서 MBTI 유형 결과가 예상과 다른 경우가 있나요? 이에 대해 어떻게 생각하시나요?"
  },
  {
    "talkie": "당신이 좋아하는 연예인이나 인물들 중에서 MBTI 유형 결과가 비슷한 사람이 있는지 알고 있나요?"
  },
  {
    "talkie": "MBTI 유형을 토대로 어떤 종류의 직업이나 취미가 잘 맞을 것 같은지 생각해본 적이 있나요?"
  },
  {
    "talkie": "MBTI 유형을 기반으로 한 커뮤니티나 사이트 등을 알고 있나요?"
  },
  {
    "talkie": "MBTI 유형 결과가 당신의 실제 성격과 일치하지 않는 경우가 있나요? 이에 대해 어떻게 생각하시나요?"
  },
  {
    "talkie": "MBTI 유형이 당신에게 자아성찰을 도와주는 데에 도움이 되는지 어떻게 생각하시나요?"
  },
  {
    "talkie": "MBTI 유형을 활용하여 관계를 개선하는 방법이나 팁이 있나요?"
  },
  {
    "talkie": "MBTI 유형 결과가 어떤 문제를 발생시키거나 논란이 될 수 있다는 이야기를 들어보았을 때 & 이에 대해서 어떻게 생각하시나요?"
  },
  {
    "talkie": "MBTI 유형 결과를 어떤 방식으로 활용하고 있는지 & 혹은 활용하고 싶은지 생각해보았나요?"
  },
  {
    "talkie": "커피 좋아하세요?"
  },
  {
    "talkie": "커피를 언제부터 좋아하게 되었나요?"
  },
  {
    "talkie": "일상생활에서 커피를 마시는 이유는 무엇인가요?"
  },
  {
    "talkie": "가장 좋아하는 커피 종류는 무엇인가요?"
  },
  {
    "talkie": "커피를 마시는 가장 좋은 시간은 언제인가요?"
  },
  {
    "talkie": "커피를 마실 때 설탕과 블랙으로 마시는 것 중 어떤 것을 선호하나요?"
  },
  {
    "talkie": "커피가 특히 맛있던 카페가 있었나요? 어디인가요?"
  },
  {
    "talkie": "어떤 커피 브랜드 좋아하세요? 그 이유는 무엇인가요?"
  },
  {
    "talkie": "어떤 커피 맛을 좋아하나요? 라이트 & 미디움 & 혹은 다크 로스트 등?"
  },
  {
    "talkie": "커피를 마시면서 좋아하는 음식은 무엇인가요?"
  },
  {
    "talkie": "가장 기억에 남는 커피 경험은 어떤 것인가요?"
  },
  {
    "talkie": "퍼스널 컬러 테스트 받아본 적 있으세요?"
  }
]